jsonp2json/__init__.py
jsonp2json/jsonp2json.py
jsonp2json-1.0.dist-info/DESCRIPTION.rst
jsonp2json-1.0.dist-info/METADATA
jsonp2json-1.0.dist-info/RECORD
jsonp2json-1.0.dist-info/WHEEL
jsonp2json-1.0.dist-info/metadata.json
jsonp2json-1.0.dist-info/top_level.txt
