Metadata-Version: 2.0
Name: jsonp2json
Version: 1.0
Summary: Converts JSONP response to JSON format
Home-page: https://github.com/tohyongcheng/jsonp2json
Author: Yong Cheng Toh
Author-email: tohyongcheng@gmail.com
License: MIT
Keywords: json,jsonp,parse,convert
Platform: UNKNOWN
Classifier: Development Status :: 3 - Alpha
Classifier: Environment :: Console
Classifier: Intended Audience :: Developers
Classifier: License :: OSI Approved :: MIT License
Classifier: Programming Language :: Python
Classifier: Programming Language :: Python :: 2
Classifier: Programming Language :: Python :: 3
